BRISC-V_single_cycle_base/src/decode.v
/** @module : decode
 *  @author : Adaptive & Secure Computing Systems (ASCS) Laboratory
 
 *  Copyright (c) 2018 BRISC-V (ASCS/ECE/BU)
 *  Permission is hereby granted, free of charge, to any person obtaining a copy
 *  of this software and associated documentation files (the "Software"), to deal
 *  in the Software without restriction, including without limitation the rights
 *  to use, copy, modify, merge, publish, distribute, sublicense, and/or sell
 *  copies of the Software, and to permit persons to whom the Software is
 *  furnished to do so, subject to the following conditions:
 *  The above copyright notice and this permission notice shall be included in
 *  all copies or substantial portions of the Software.

 *  THE SOFTWARE IS PROVIDED "AS IS", WITHOUT WARRANTY OF ANY KIND, EXPRESS OR
 *  IMPLIED, INCLUDING BUT NOT LIMITED TO THE WARRANTIES OF MERCHANTABILITY,
 *  FITNESS FOR A PARTICULAR PURPOSE AND NONINFRINGEMENT. IN NO EVENT SHALL THE
 *  AUTHORS OR COPYRIGHT HOLDERS BE LIABLE FOR ANY CLAIM, DAMAGES OR OTHER
 *  LIABILITY, WHETHER IN AN ACTION OF CONTRACT, TORT OR OTHERWISE, ARISING FROM,
 *  OUT OF OR IN CONNECTION WITH THE SOFTWARE OR THE USE OR OTHER DEALINGS IN
 *  THE SOFTWARE.
 */
 // 32-bit Decoder

module regFile (
                clock, reset, read_sel1, read_sel2,
                wEn, write_sel, write_data, 
                read_data1, read_data2
);

parameter REG_DATA_WIDTH = 32, REG_SEL_BITS = 5;

input clock, reset, wEn; 
input [REG_DATA_WIDTH-1:0] write_data;
input [REG_SEL_BITS-1:0] read_sel1, read_sel2, write_sel;
output[REG_DATA_WIDTH-1:0] read_data1; 
output[REG_DATA_WIDTH-1:0] read_data2; 

//(* ram_style = "distributed" *) 
reg   [REG_DATA_WIDTH-1:0] register_file[0:(1<<REG_SEL_BITS)-1];
integer i; 

always @(posedge clock)
    if(reset==1)
        register_file[0] <= 0; 
    else 
        if (wEn & write_sel != 0) register_file[write_sel] <= write_data;
          
//----------------------------------------------------
// Drive the outputs
//----------------------------------------------------
assign  read_data1 = register_file[read_sel1];
assign  read_data2 = register_file[read_sel2];

endmodule

//----------------------------------------------------------------decode unit----------------------------------------//
module decode_unit (
      clock, reset, 
      PC, instruction, 
      extend_sel,
      write, write_reg, write_data, 
      
      opcode, funct3, funct7,
      rs1_data, rs2_data, rd, 
      extend_imm,
      branch_target, 
      JAL_target,  
      report
); 

parameter CORE = 0, ADDRESS_BITS = 20;
 
input  clock; 
input  reset; 

input  [ADDRESS_BITS-1:0] PC;
input  [31:0] instruction; 
input  [1:0] extend_sel; 
input  write;
input  [4:0]  write_reg;
input  [31:0] write_data;

output [31:0] rs1_data; 
output [31:0] rs2_data;
output [4:0]  rd;  
output [6:0]  opcode;
output [6:0]  funct7; 
output [2:0]  funct3;
output [31:0] extend_imm;
output [ADDRESS_BITS-1:0] branch_target; 
output [ADDRESS_BITS-1:0] JAL_target;

input report; 

// Read registers
wire[4:0]  rs2        = instruction[24:20];
wire[4:0]  rs1        = instruction[19:15];

wire[11:0] i_imm      = instruction[31:20];
wire[6:0]  s_imm_msb  = instruction[31:25];
wire[4:0]  s_imm_lsb  = instruction[11:7];
wire[19:0] u_imm      = instruction[31:12];
wire[11:0] i_imm_orig = instruction[31:20]; 
wire[19:0] uj_imm     = {instruction[31],instruction[19:12],instruction[20],instruction[30:21]};

//Forming the s immediate value from the two msb and lsb parts of the s immediate
wire[11:0] s_imm_orig     = {s_imm_msb,s_imm_lsb};
wire[12:0] sb_imm_orig    = {s_imm_msb[6],s_imm_lsb[0],s_imm_msb[5:0],s_imm_lsb[4:1],1'b0};

/* Instruction decoding */
assign opcode        = instruction[6:0];
assign funct7        = instruction[31:25];
assign funct3        = instruction[14:12];

/* Write register */
assign  rd           = instruction[11:7];

/* Only workig with BEQ at the moment */
wire[31:0] sb_imm_32      = {{19{sb_imm_orig[12]}}, sb_imm_orig};
assign branch_target      = PC + sb_imm_32;

/* Extensions */
wire[31:0] u_imm_32       = {u_imm,12'b0};
wire[31:0] i_imm_32       = {{20{i_imm_orig[11]}}, i_imm_orig[11:0] };
wire[31:0] s_imm_32       = {{20{s_imm_orig[11]}}, s_imm_orig};

assign extend_imm         = (extend_sel == 2'b01)? s_imm_32 : 
                            (extend_sel == 2'b10)? u_imm_32 : i_imm_32;
                            
/* Only JAL Target. JALR happens in the execution unit*/
wire[31:0] uj_imm_32      = {{11{uj_imm[19]}},uj_imm[19:0],1'b0}; 
assign JAL_target         = uj_imm_32 + PC;
 
regFile #(32, 5) registers (
                .clock(clock), 
                .reset(reset), 
                .read_sel1(rs1), 
                .read_sel2(rs2),
                .wEn(write), 
                .write_sel(write_reg), 
                .write_data(write_data), 
                .read_data1(rs1_data), 
                .read_data2(rs2_data)
);

reg [31: 0] cycles; 
always @ (posedge clock) begin 
    cycles <= reset? 0 : cycles + 1; 
    if (report)begin
        $display ("------ Core %d Decode Unit - Current Cycle %d -------", CORE, cycles); 
        $display ("| PC          [%h]", PC);
        $display ("| Instruction [%h]", instruction);
        $display ("| rs1         [%d]", rs1);
        $display ("| rs1_data    [%d]", rs1_data);
        $display ("| rs2         [%d]", rs2);
        $display ("| rs2_data    [%d]", rs2_data);
        $display ("| rsd         [%d]", rd);
        $display ("| jumpTarget  [%h]", JAL_target);
        $display ("| branchTarget[%h]", branch_target);
        $display ("| Opcode      [%b]    Funct3 [%b]      Funct7  [%b]", opcode, funct3, funct7);
        $display ("| Immediate   [%d] Hex    [%h] Bin     [%b]", extend_imm, extend_imm, extend_imm[7:0]);
        $display ("| write       [%b]", write);
        $display ("| write_reg   [%d]", write_reg);
        $display ("| write_data  [%d]", write_data);
        $display ("----------------------------------------------------------------------");
    end
end

endmodule
//------------------------------decode test bench-----------------------------------------------//
module tb_decode_unit (); 

reg clk, reset;  

reg  [31:0] PC;
reg  [31:0] instruction; 
reg  [1:0] extend_sel; 
reg  write;
reg  [4:0]  write_reg;
reg  [31:0] write_data;
reg  report; 

wire [31:0]  rs1_data; 
wire [31:0]  rs2_data;
wire [4:0]   rd;  
wire [31:0] branch_target; 
wire [31:0] JAL_target;

wire [6:0]  opcode;
wire [6:0]  funct7; 
wire [2:0]  funct3;
wire [31:0] extend_imm;

decode_unit #(0, 32) decode (
      .clock(clk),
      .reset(reset), 
      .PC(PC),
      .instruction(instruction),
      .extend_sel(extend_sel),
      .write(write),
      .write_reg(write_reg),
      .write_data(write_data), 
      
      .opcode(opcode),
      .funct3(funct3),
      .funct7(funct7),
      .rs1_data(rs1_data),
      .rs2_data(rs2_data),
      .rd(rd),
      .extend_imm(extend_imm), 
      .branch_target(branch_target), 
      .JAL_target(JAL_target), 
      .report(report)
); 

// Clock generator
always #1 clk = ~clk;

initial begin
  $dumpfile ("decode.vcd");
  $dumpvars();
  clk   = 0;
  reset = 1;
  PC            = 0; 
  instruction   = 0; 
  extend_sel    = 0; 
  write         = 0; 
  write_data    = 0; 
  write_reg     = 0;
  report        = 1; 
  
  #10 reset = 0; 
  $display (" --- Start --- ");
  repeat (1) @ (posedge clk);
  
  PC            <= 4; 
  instruction   <= 32'hfe010113; 
  write         <= 0; 
  write_data    <= 0; 
  write_reg     <= 0;
  repeat (1) @ (posedge clk);
  
  PC            <= 8; 
  instruction   <= 32'h00112e23; 
  write         <= 0; 
  write_data    <= 0; 
  write_reg     <= 0;
  repeat (1) @ (posedge clk);
  
  PC            <= 32'h0C; 
  instruction   <= 32'h00812c23; 
  write         <= 0; 
  write_data    <= 0; 
  write_reg     <= 0;
  repeat (1) @ (posedge clk);
  
  PC            <= 32'h10; 
  instruction   <= 32'h02010413; 
  write         <= 0; 
  write_data    <= 0; 
  write_reg     <= 0;
  repeat (1) @ (posedge clk);
  
  PC            <= 32'h14; 
  instruction   <= 32'h00400793; 
  write         <= 0; 
  write_data    <= 0; 
  write_reg     <= 0;
  repeat (1) @ (posedge clk);
  
  PC            <= 32'h18; 
  instruction   <= 32'hfef42623; 
  write         <= 0; 
  write_data    <= 0; 
  write_reg     <= 0;
  repeat (1) @ (posedge clk);
  #200 $finish;
  end

endmodule

BRISC-V_single_cycle_base/src/decode.vcd
$date
      Sun Mar 26 19:40:11 2023

$end
$version
      Veriwell 2.8.7
$end
$timescale
      1s
$end


$scope module tb_decode_unit $end
$var reg       1 !    clk  $end
$var reg       1 "    reset  $end
$var reg      32 #    PC [31:0] $end
$var reg      32 $    instruction [31:0] $end
$var reg       2 %    extend_sel [1:0] $end
$var reg       1 &    write  $end
$var reg       5 '    write_reg [4:0] $end
$var reg      32 (    write_data [31:0] $end
$var reg       1 )    report  $end
$var wire     32 *    rs1_data [31:0] $end
$var wire     32 +    rs2_data [31:0] $end
$var wire      5 ,    rd [4:0] $end
$var wire     32 -    branch_target [31:0] $end
$var wire     32 .    JAL_target [31:0] $end
$var wire      7 /    opcode [6:0] $end
$var wire      7 0    funct7 [6:0] $end
$var wire      3 1    funct3 [2:0] $end
$var wire     32 2    extend_imm [31:0] $end

$scope module decode $end
$var wire      1 3    report  $end
$var wire     32 4    JAL_target [31:0] $end
$var wire     32 5    branch_target [31:0] $end
$var wire     32 6    extend_imm [31:0] $end
$var wire      3 7    funct3 [2:0] $end
$var wire      7 8    funct7 [6:0] $end
$var wire      7 9    opcode [6:0] $end
$var wire      5 :    rd [4:0] $end
$var wire     32 ;    rs2_data [31:0] $end
$var wire     32 <    rs1_data [31:0] $end
$var wire     32 =    write_data [31:0] $end
$var wire      5 >    write_reg [4:0] $end
$var wire      1 ?    write  $end
$var wire      2 @    extend_sel [1:0] $end
$var wire     32 A    instruction [31:0] $end
$var wire     32 B    PC [31:0] $end
$var wire      1 C    reset  $end
$var wire      1 D    clock  $end
$var wire      5 E    rs2 [4:0] $end
$var wire      5 F    rs1 [4:0] $end
$var wire     12 G    i_imm [11:0] $end
$var wire      7 H    s_imm_msb [6:0] $end
$var wire      5 I    s_imm_lsb [4:0] $end
$var wire     20 J    u_imm [19:0] $end
$var wire     12 K    i_imm_orig [11:0] $end
$var wire     20 L    uj_imm [19:0] $end
$var wire     12 M    s_imm_orig [11:0] $end
$var wire     13 N    sb_imm_orig [12:0] $end
$var wire     32 O    sb_imm_32 [31:0] $end
$var wire     32 P    u_imm_32 [31:0] $end
$var wire     32 Q    i_imm_32 [31:0] $end
$var wire     32 R    s_imm_32 [31:0] $end
$var wire     32 S    uj_imm_32 [31:0] $end
$var reg      32 T    cycles [31:0] $end

$scope module registers $end
$var wire     32 U    read_data2 [31:0] $end
$var wire     32 V    read_data1 [31:0] $end
$var wire      5 W    write_sel [4:0] $end
$var wire      5 X    read_sel2 [4:0] $end
$var wire      5 Y    read_sel1 [4:0] $end
$var wire     32 Z    write_data [31:0] $end
$var wire      1 [    wEn  $end
$var wire      1 \    reset  $end
$var wire      1 ]    clock  $end
$var integer    32 ^    i  $end
$upscope $end

$upscope $end

$upscope $end

$enddefinitions      $end
#0
$dumpvars
bx ^
0]
1\
0[
b0 Z
b0 Y
b0 X
b0 W
bx V
bx U
bx T
b0 S
b0 R
b0 Q
b0 P
b0 O
b0 N
b0 M
b0 L
b0 K
b0 J
b0 I
b0 H
b0 G
b0 F
b0 E
0D
1C
b0 B
b0 A
b0 @
0?
b0 >
b0 =
bx <
bx ;
b0 :
b0 9
b0 8
b0 7
b0 6
b0 5
b0 4
13
b0 2
b0 1
b0 0
b0 /
b0 .
b0 -
b0 ,
bx +
bx *
1)
b0 (
b0 '
0&
b0 %
b0 $
b0 #
1"
0!
$end
#1
1!
1]
1D
b0 T
b0 U
b0 ;
b0 +
b0 V
b0 <
b0 *
#2
0!
0]
0D
#3
1!
1]
1D
#4
0!
0]
0D
#5
1!
1]
1D
#6
0!
0]
0D
#7
1!
1]
1D
#8
0!
0]
0D
#9
1!
1]
1D
#10
0"
0!
0\
0C
0]
0D
#11
1!
1]
1D
b100 #
b11111110000000010000000100010011 $
b1 T
b100 B
b11111111111100010000011111100000 S
b10001000001111110000 L
b11111111111111111111111111100000 Q
b111111100000 K
b11111110000000010000000000000000 P
b11111110000000010000 J
b10 O
b10 N
b10 R
b10 M
b10 I
b11111111111111111111011111100010 O
b1011111100010 N
b11111111111111111111111111100010 R
b111111100010 M
b1111111 H
b111111100000 G
b10 Y
b10 F
b11111110000000010000000100010011 A
b11111111111100010000011111100100 4
b11111111111100010000011111100100 .
b11111111111111111111011111100110 5
b11111111111111111111011111100110 -
b10 :
b10 ,
b1111111 8
b1111111 0
b10011 9
b10011 /
b11111111111111111111111111100000 6
b11111111111111111111111111100000 2
bx V
bx <
bx *
#12
0!
0]
0D
#13
1!
1]
1D
b1000 #
b100010010111000100011 $
b10 T
b1000 B
b10010100000000000 S
b1001010000000000 L
b1 Q
b1 K
b100010010000000000000 P
b100010010 J
b11111111111111111111011111111100 O
b1011111111100 N
b11111111111111111111111111111100 R
b111111111100 M
b11100 I
b11100 O
b11100 N
b11100 R
b11100 M
b0 H
b1 G
b1 X
b1 E
b100010010111000100011 A
b10010100000001000 4
b10010100000001000 .
b100100 5
b100100 -
b11100 :
b11100 ,
b10 7
b10 1
b0 8
b0 0
b100011 9
b100011 /
b1 6
b1 2
bx U
bx ;
bx +
#14
0!
0]
0D
#15
1!
1]
1D
b1100 #
b100000010010110000100011 $
b11 T
b1100 B
b10010000000001000 S
b1001000000000100 L
b1000 Q
b1000 K
b100000010010000000000000 P
b100000010010 J
b11000 O
b11000 N
b11000 R
b11000 M
b11000 I
b1000 G
b1000 X
b1000 E
b100000010010110000100011 A
b10010000000010100 4
b10010000000010100 .
b11000 :
b11000 ,
b1000 6
b1000 2
#16
0!
0]
0D
#17
1!
1]
1D
b10000 #
b10000000010000010000010011 $
b100 T
b10000 B
b10000000000100000 S
b1000000000010000 L
b100000 Q
b100000 K
b10000000010000000000000000 P
b10000000010000 J
b1000 O
b1000 N
b1000 R
b1000 M
b1000 I
b101000 O
b101000 N
b101000 R
b101000 M
b1 H
b100000 G
b0 X
b0 E
b10000000010000010000010011 A
b10000000000110000 4
b10000000000110000 .
b111000 5
b111000 -
b1000 :
b1000 ,
b0 7
b0 1
b1 8
b1 0
b10011 9
b10011 /
b100000 6
b100000 2
b0 U
b0 ;
b0 +
#18
0!
0]
0D
#19
1!
1]
1D
b10100 #
b10000000000011110010011 $
b101 T
b10100 B
b100 S
b10 L
b100 Q
b100 K
b10000000000000000000000 P
b10000000000 J
b100000101110 O
b100000101110 N
b101111 R
b101111 M
b1111 I
b100000001110 O
b100000001110 N
b1111 R
b1111 M
b0 H
b100 G
b0 Y
b0 F
b100 X
b100 E
b10000000000011110010011 A
b11000 4
b11000 .
b100000100010 5
b100000100010 -
b1111 :
b1111 ,
b0 8
b0 0
b100 6
b100 2
b0 V
b0 <
b0 *
bx U
bx ;
bx +
#20
0!
0]
0D
#21
1!
1]
1D
b11000 #
b11111110111101000010011000100011 $
b110 T
b11000 B
b11111111111101000010111111101110 S
b10100001011111110111 L
b11111111111111111111111111101111 Q
b111111101111 K
b11111110111101000010000000000000 P
b11111110111101000010 J
b1100 O
b1100 N
b1100 R
b1100 M
b1100 I
b11111111111111111111011111101100 O
b1011111101100 N
b11111111111111111111111111101100 R
b111111101100 M
b1111111 H
b111111101111 G
b1000 Y
b1000 F
b1111 X
b1111 E
b11111110111101000010011000100011 A
b11111111111101000011000000000110 4
b11111111111101000011000000000110 .
b11111111111111111111100000000100 5
b11111111111111111111100000000100 -
b1100 :
b1100 ,
b10 7
b10 1
b1111111 8
b1111111 0
b100011 9
b100011 /
b11111111111111111111111111101111 6
b11111111111111111111111111101111 2
bx V
bx <
bx *
#22
0!
0]
0D
#23
1!
1]
1D
b111 T
#24
0!
0]
0D
#25
1!
1]
1D
b1000 T
#26
0!
0]
0D
#27
1!
1]
1D
b1001 T
#28
0!
0]
0D
#29
1!
1]
1D
b1010 T
#30
0!
0]
0D
#31
1!
1]
1D
b1011 T
#32
0!
0]
0D
#33
1!
1]
1D
b1100 T
#34
0!
0]
0D
#35
1!
1]
1D
b1101 T
#36
0!
0]
0D
#37
1!
1]
1D
b1110 T
#38
0!
0]
0D
#39
1!
1]
1D
b1111 T
#40
0!
0]
0D
#41
1!
1]
1D
b10000 T
#42
0!
0]
0D
#43
1!
1]
1D
b10001 T
#44
0!
0]
0D
#45
1!
1]
1D
b10010 T
#46
0!
0]
0D
#47
1!
1]
1D
b10011 T
#48
0!
0]
0D
#49
1!
1]
1D
b10100 T
#50
0!
0]
0D
#51
1!
1]
1D
b10101 T
#52
0!
0]
0D
#53
1!
1]
1D
b10110 T
#54
0!
0]
0D
#55
1!
1]
1D
b10111 T
#56
0!
0]
0D
#57
1!
1]
1D
b11000 T
#58
0!
0]
0D
#59
1!
1]
1D
b11001 T
#60
0!
0]
0D
#61
1!
1]
1D
b11010 T
#62
0!
0]
0D
#63
1!
1]
1D
b11011 T
#64
0!
0]
0D
#65
1!
1]
1D
b11100 T
#66
0!
0]
0D
#67
1!
1]
1D
b11101 T
#68
0!
0]
0D
#69
1!
1]
1D
b11110 T
#70
0!
0]
0D
#71
1!
1]
1D
b11111 T
#72
0!
0]
0D
#73
1!
1]
1D
b100000 T
#74
0!
0]
0D
#75
1!
1]
1D
b100001 T
#76
0!
0]
0D
#77
1!
1]
1D
b100010 T
#78
0!
0]
0D
#79
1!
1]
1D
b100011 T
#80
0!
0]
0D
#81
1!
1]
1D
b100100 T
#82
0!
0]
0D
#83
1!
1]
1D
b100101 T
#84
0!
0]
0D
#85
1!
1]
1D
b100110 T
#86
0!
0]
0D
#87
1!
1]
1D
b100111 T
#88
0!
0]
0D
#89
1!
1]
1D
b101000 T
#90
0!
0]
0D
#91
1!
1]
1D
b101001 T
#92
0!
0]
0D
#93
1!
1]
1D
b101010 T
#94
0!
0]
0D
#95
1!
1]
1D
b101011 T
#96
0!
0]
0D
#97
1!
1]
1D
b101100 T
#98
0!
0]
0D
#99
1!
1]
1D
b101101 T
#100
0!
0]
0D
#101
1!
1]
1D
b101110 T
#102
0!
0]
0D
#103
1!
1]
1D
b101111 T
#104
0!
0]
0D
#105
1!
1]
1D
b110000 T
#106
0!
0]
0D
#107
1!
1]
1D
b110001 T
#108
0!
0]
0D
#109
1!
1]
1D
b110010 T
#110
0!
0]
0D
#111
1!
1]
1D
b110011 T
#112
0!
0]
0D
#113
1!
1]
1D
b110100 T
#114
0!
0]
0D
#115
1!
1]
1D
b110101 T
#116
0!
0]
0D
#117
1!
1]
1D
b110110 T
#118
0!
0]
0D
#119
1!
1]
1D
b110111 T
#120
0!
0]
0D
#121
1!
1]
1D
b111000 T
#122
0!
0]
0D
#123
1!
1]
1D
b111001 T
#124
0!
0]
0D
#125
1!
1]
1D
b111010 T
#126
0!
0]
0D
#127
1!
1]
1D
b111011 T
#128
0!
0]
0D
#129
1!
1]
1D
b111100 T
#130
0!
0]
0D
#131
1!
1]
1D
b111101 T
#132
0!
0]
0D
#133
1!
1]
1D
b111110 T
#134
0!
0]
0D
#135
1!
1]
1D
b111111 T
#136
0!
0]
0D
#137
1!
1]
1D
b1000000 T
#138
0!
0]
0D
#139
1!
1]
1D
b1000001 T
#140
0!
0]
0D
#141
1!
1]
1D
b1000010 T
#142
0!
0]
0D
#143
1!
1]
1D
b1000011 T
#144
0!
0]
0D
#145
1!
1]
1D
b1000100 T
#146
0!
0]
0D
#147
1!
1]
1D
b1000101 T
#148
0!
0]
0D
#149
1!
1]
1D
b1000110 T
#150
0!
0]
0D
#151
1!
1]
1D
b1000111 T
#152
0!
0]
0D
#153
1!
1]
1D
b1001000 T
#154
0!
0]
0D
#155
1!
1]
1D
b1001001 T
#156
0!
0]
0D
#157
1!
1]
1D
b1001010 T
#158
0!
0]
0D
#159
1!
1]
1D
b1001011 T
#160
0!
0]
0D
#161
1!
1]
1D
b1001100 T
#162
0!
0]
0D
#163
1!
1]
1D
b1001101 T
#164
0!
0]
0D
#165
1!
1]
1D
b1001110 T
#166
0!
0]
0D
#167
1!
1]
1D
b1001111 T
#168
0!
0]
0D
#169
1!
1]
1D
b1010000 T
#170
0!
0]
0D
#171
1!
1]
1D
b1010001 T
#172
0!
0]
0D
#173
1!
1]
1D
b1010010 T
#174
0!
0]
0D
#175
1!
1]
1D
b1010011 T
#176
0!
0]
0D
#177
1!
1]
1D
b1010100 T
#178
0!
0]
0D
#179
1!
1]
1D
b1010101 T
#180
0!
0]
0D
#181
1!
1]
1D
b1010110 T
#182
0!
0]
0D
#183
1!
1]
1D
b1010111 T
#184
0!
0]
0D
#185
1!
1]
1D
b1011000 T
#186
0!
0]
0D
#187
1!
1]
1D
b1011001 T
#188
0!
0]
0D
#189
1!
1]
1D
b1011010 T
#190
0!
0]
0D
#191
1!
1]
1D
b1011011 T
#192
0!
0]
0D
#193
1!
1]
1D
b1011100 T
#194
0!
0]
0D
#195
1!
1]
1D
b1011101 T
#196
0!
0]
0D
#197
1!
1]
1D
b1011110 T
#198
0!
0]
0D
#199
1!
1]
1D
b1011111 T
#200
0!
0]
0D
#201
1!
1]
1D
b1100000 T
#202
0!
0]
0D
#203
1!
1]
1D
b1100001 T
#204
0!
0]
0D
#205
1!
1]
1D
b1100010 T
#206
0!
0]
0D
#207
1!
1]
1D
b1100011 T
#208
0!
0]
0D
#209
1!
1]
1D
b1100100 T
#210
0!
0]
0D
#211
1!
1]
1D
b1100101 T
#212
0!
0]
0D
#213
1!
1]
1D
b1100110 T
#214
0!
0]
0D
#215
1!
1]
1D
b1100111 T
#216
0!
0]
0D
#217
1!
1]
1D
b1101000 T
#218
0!
0]
0D
#219
1!
1]
1D
b1101001 T
#220
0!
0]
0D
#221
1!
1]
1D
b1101010 T
