BRISC-V_single_cycle_base/src/fetch.v
/** @module : fetch_unit
 *  @author : Adaptive & Secure Computing Systems (ASCS) Laboratory

 *  Copyright (c) 2018 BRISC-V (ASCS/ECE/BU)
 *  Permission is hereby granted, free of charge, to any person obtaining a copy
 *  of this software and associated documentation files (the "Software"), to deal
 *  in the Software without restriction, including without limitation the rights
 *  to use, copy, modify, merge, publish, distribute, sublicense, and/or sell
 *  copies of the Software, and to permit persons to whom the Software is
 *  furnished to do so, subject to the following conditions:
 *  The above copyright notice and this permission notice shall be included in
 *  all copies or substantial portions of the Software.

 *  THE SOFTWARE IS PROVIDED "AS IS", WITHOUT WARRANTY OF ANY KIND, EXPRESS OR
 *  IMPLIED, INCLUDING BUT NOT LIMITED TO THE WARRANTIES OF MERCHANTABILITY,
 *  FITNESS FOR A PARTICULAR PURPOSE AND NONINFRINGEMENT. IN NO EVENT SHALL THE
 *  AUTHORS OR COPYRIGHT HOLDERS BE LIABLE FOR ANY CLAIM, DAMAGES OR OTHER
 *  LIABILITY, WHETHER IN AN ACTION OF CONTRACT, TORT OR OTHERWISE, ARISING FROM,
 *  OUT OF OR IN CONNECTION WITH THE SOFTWARE OR THE USE OR OTHER DEALINGS IN
 *  THE SOFTWARE.
 */
/** @module : memory_interface
 *  @author : Adaptive & Secure Computing Systems (ASCS) Laboratory

 *  Copyright (c) 2018 BRISC-V (ASCS/ECE/BU)
 *  Permission is hereby granted, free of charge, to any person obtaining a copy
 *  of this software and associated documentation files (the "Software"), to deal
 *  in the Software without restriction, including without limitation the rights
 *  to use, copy, modify, merge, publish, distribute, sublicense, and/or sell
 *  copies of the Software, and to permit persons to whom the Software is
 *  furnished to do so, subject to the following conditions:
 *  The above copyright notice and this permission notice shall be included in
 *  all copies or substantial portions of the Software.

 *  THE SOFTWARE IS PROVIDED "AS IS", WITHOUT WARRANTY OF ANY KIND, EXPRESS OR
 *  IMPLIED, INCLUDING BUT NOT LIMITED TO THE WARRANTIES OF MERCHANTABILITY,
 *  FITNESS FOR A PARTICULAR PURPOSE AND NONINFRINGEMENT. IN NO EVENT SHALL THE
 *  AUTHORS OR COPYRIGHT HOLDERS BE LIABLE FOR ANY CLAIM, DAMAGES OR OTHER
 *  LIABILITY, WHETHER IN AN ACTION OF CONTRACT, TORT OR OTHERWISE, ARISING FROM,
 *  OUT OF OR IN CONNECTION WITH THE SOFTWARE OR THE USE OR OTHER DEALINGS IN
 *  THE SOFTWARE.
 
 
 */
 //(* ram_style = "block" *)
module BSRAM (
        clock,
        reset,
        readEnable,
        readAddress,
        readData,
        writeEnable,
        writeAddress,
        writeData, 
        report
); 
parameter CORE = 0, DATA_WIDTH = 32, ADDR_WIDTH = 8;
parameter MEM_DEPTH = 1 << ADDR_WIDTH;

input clock; 
input reset; 
input readEnable;
input [ADDR_WIDTH-1:0]   readAddress;
output [DATA_WIDTH-1:0]  readData;
input writeEnable;
input [ADDR_WIDTH-1:0]   writeAddress;
input [DATA_WIDTH-1:0]   writeData;
input report; 
 
wire [DATA_WIDTH-1:0]     readData;
reg  [DATA_WIDTH-1:0]     sram [0:MEM_DEPTH-1];
 
//--------------Code Starts Here------------------ 
assign readData = (readEnable & writeEnable & (readAddress == writeAddress))? 
                  writeData : readEnable? sram[readAddress] : 0;

always@(posedge clock) begin : RAM_WRITE
    if(writeEnable)
        sram[writeAddress] <= writeData;
end

reg [31: 0] cycles; 
always @ (posedge clock) begin 
    cycles <= reset? 0 : cycles + 1; 
    if (report)begin
        $display ("------ Core %d SBRAM Unit - Current Cycle %d --------", CORE, cycles); 
        $display ("| Read        [%b]", readEnable);
        $display ("| Read Address[%h]", readAddress);
        $display ("| Read Data   [%h]", readData);
        $display ("| Write       [%b]", writeEnable);
        $display ("| Write Addres[%h]", writeAddress);
        $display ("| Write Data  [%h]", writeData);
        $display ("----------------------------------------------------------------------");
    end 
 end    

endmodule


 //-----------------------------------------------------MEM_INTERFACE----------------------------//
module mem_interface (
                     clock, reset,
                     read, write, write_address, read_address, in_data,
                     out_addr, out_data, valid, ready,
                     report
);
parameter CORE = 0, DATA_WIDTH = 32, INDEX_BITS = 6,
                     OFFSET_BITS = 3, ADDRESS_BITS = 20;

input clock, reset;
input read, write;
input [ADDRESS_BITS-1:0] write_address;
input [ADDRESS_BITS-1:0] read_address;
input [DATA_WIDTH-1:0]   in_data;
output valid, ready;
output[ADDRESS_BITS-1:0] out_addr;
output[DATA_WIDTH-1:0]   out_data;

input  report;


BSRAM #(CORE, DATA_WIDTH, ADDRESS_BITS) RAM (
        .clock(clock),
        .reset(reset),
        .readEnable(read),
        .readAddress(read_address),
        .readData(out_data),

        .writeEnable(write),
        .writeAddress(write_address),
        .writeData(in_data),

        .report(report)
);

assign out_addr = read? read_address : 0;
assign valid    = (read | write)? 1 : 0;
assign ready    = (read | write)? 0 : 1; /// Just for testing now

reg [31: 0] cycles;
always @ (posedge clock) begin
    cycles <= reset? 0 : cycles + 1;
    if (report)begin
        $display ("------ Core %d Memory Interface - Current Cycle %d --", CORE, cycles);
        
        $display ("| Read Address     [%h]", read_address);
        $display ("| Read        [%b]", read);
        $display ("| Write Address     [%h]", write_address);
        $display ("| Write       [%b]", write);
        $display ("| Out Data    [%h]", out_data);
        $display ("| In Data     [%h]", in_data);
        $display ("| Ready       [%b]", ready);
        $display ("| Valid       [%b]", valid);
        $display ("----------------------------------------------------------------------");
    end
end

endmodule

//---------------------------------fetch unit------------------------------------------------------//
module fetch_unit(
        clock, reset, start,

        PC_select,
        program_address,
        JAL_target,
        JALR_target,
        branch,
        branch_target,

        // In-System Programmer Interface
        isp_address,
        isp_data,
        isp_write,

        instruction,
        inst_PC,
        valid,
        ready,
        report
);

parameter CORE = 0, DATA_WIDTH = 32, INDEX_BITS = 4,
                     OFFSET_BITS = 3, ADDRESS_BITS = 28;

input clock, reset, start;
input [1:0] PC_select;

input [ADDRESS_BITS-1:0] program_address;
input [ADDRESS_BITS-1:0] JAL_target;
input [ADDRESS_BITS-1:0] JALR_target;
input branch;
input [ADDRESS_BITS-1:0] branch_target;

// In-System Programmer Interface
input [ADDRESS_BITS-1:0] isp_address;
input [DATA_WIDTH-1:0] isp_data;
input isp_write;

output [DATA_WIDTH-1:0]   instruction;
output [ADDRESS_BITS-1:0] inst_PC;
output valid;
output ready;

input report;

reg [ADDRESS_BITS-1:0] old_PC;
reg fetch;

reg  [ADDRESS_BITS-1:0] PC_reg;
wire [ADDRESS_BITS-1:0] PC = reset? program_address : PC_reg;
wire [ADDRESS_BITS-1:0] PC_plus4 = PC + 4;

//Adjustment to be word addressable instruction addresses
wire [ADDRESS_BITS-1:0] inst_addr = PC >> 2;
wire [ADDRESS_BITS-1:0] out_addr;
assign inst_PC =  out_addr << 2;

mem_interface #(CORE, DATA_WIDTH, INDEX_BITS, OFFSET_BITS, ADDRESS_BITS)
                    i_mem_interface (
                     .clock(clock),
                     .reset(reset),
                     .read(fetch),
                     .write(isp_write),
                     .write_address(isp_address),
                     .read_address(inst_addr),
                     .in_data(isp_data),
                     .out_addr(out_addr),
                     .out_data(instruction),
                     .valid(valid),
                     .ready(ready),
                     .report(report)
);

always @ (posedge clock) begin
      if (reset) begin 
        fetch        <= 0; 
        PC_reg       <= 0;  
        old_PC       <= 0; 
      end 
      else begin 
        if (start) begin 
            fetch        <= 1;
            PC_reg       <= program_address;            
            old_PC       <= 0; 
        end 
        else begin 
            fetch        <= 1;
            PC_reg       <= (PC_select == 2'b10)?  JAL_target: 
                            (PC_select == 2'b11)?  JALR_target: 
                            ((PC_select == 2'b01)& branch)?  branch_target : PC_plus4;  
            old_PC       <= PC_reg; 
        end
      end
end

reg [31: 0] cycles; 
always @ (posedge clock) begin 
    cycles <= reset? 0 : cycles + 1; 
    if (report)begin
        $display ("------ Core %d Fetch Unit - Current Cycle %d --------", CORE, cycles); 
        $display ("| Prog_Address[%h]", program_address);
        $display ("| Control     [%b]", PC_select);
        $display ("| PC          [%h]", PC);
        $display ("| old_PC      [%h]", old_PC);
        $display ("| PC_plus4    [%h]", PC_plus4);
        $display ("| JAL_target  [%h]", JAL_target);
        $display ("| JALR_target [%h]", JALR_target);
        $display ("| Branch      [%b]", branch);
        $display ("| branchTarget[%h]", branch_target);
        $display ("| Read        [%b]", fetch);
        $display ("| instruction [%h]", instruction);
        $display ("| inst_PC     [%h]", inst_PC);
        $display ("| Ready       [%b]", ready);
        $display ("| Valid       [%b]", valid);
        $display ("----------------------------------------------------------------------");
    end
end

endmodule
//----------------------------------testbench--------------------------------------------------------//

/** @module : tb_fetch_unit
 *  @author : Adaptive & Secure Computing Systems (ASCS) Laboratory
 *  Copyright (c) 2018 BRISC-V (ASCS/ECE/BU)
 */

module tb_fetch_unit (); 

reg clk, reset, start; 
reg [1:0] PC_select;

reg [7:0] program_address;
reg [7:0] JAL_target;
reg [7:0] JALR_target;
reg branch; 
reg [7:0] branch_target;
reg report;

wire [31:0]   instruction;
wire [7:0]    inst_PC;  
wire valid; 
wire ready; 

//module fetch_unit #(parameter CORE = 0, DATA_WIDTH = 32, INDEX_BITS = 6, 
//                     OFFSET_BITS = 3, ADDRESS_BITS = 20)
                     
fetch_unit IF (
        .clock(clk),
        .reset(reset),
        .start(start),
        
        .PC_select(PC_select),
        .program_address(program_address), 
        .JAL_target(JAL_target),
        .JALR_target(JALR_target),
        .branch(branch),
        .branch_target(branch_target), 
        
        .isp_address(isp_address),
        .isp_data(isp_data),
        .isp_write(isp_write),
        
        .instruction(instruction), 
        .inst_PC(inst_PC),
        .valid(valid),
        .ready(ready),
        .report(report)
); 

// Clock generator
always #1 clk = ~clk;

initial begin
  $dumpfile ("fetch_unit.vcd");
  $dumpvars();
  clk   = 0;
  reset = 1;
  start = 1;
  
  program_address = 0; 
  JAL_target      = 0; 
  JALR_target     = 0; 
  branch          = 0; 
  branch_target   = 2; 
  PC_select       = 0; 
  report          = 1; 
  
  #8  reset = 0; 
  #10 start = 0;
  $display (" --- Start --- ");
  repeat (1) @ (posedge clk);
  
  PC_select<= 1;
  repeat (1) @ (posedge clk);
  
  PC_select<= 2;
  repeat (1) @ (posedge clk);
  
  PC_select<= 3;
  repeat (1) @ (posedge clk);
  
  PC_select<= 4;
  repeat (1) @ (posedge clk);
  
  PC_select<= 5;
  repeat (1) @ (posedge clk);
  
  PC_select<= 1;
  repeat (1) @ (posedge clk);
  #200 $finish;
  end

endmodule

BRISC-V_single_cycle_base/src/fetch_unit.vcd
$date
      Mon Mar 27 07:40:39 2023

$end
$version
      Veriwell 2.8.7
$end
$timescale
      1s
$end


$scope module tb_fetch_unit $end
$var reg       1 !    clk  $end
$var reg       1 "    reset  $end
$var reg       1 #    start  $end
$var reg       2 $    PC_select [1:0] $end
$var reg       8 %    program_address [7:0] $end
$var reg       8 &    JAL_target [7:0] $end
$var reg       8 '    JALR_target [7:0] $end
$var reg       1 (    branch  $end
$var reg       8 )    branch_target [7:0] $end
$var reg       1 *    report  $end
$var wire     32 +    instruction [31:0] $end
$var wire      8 ,    inst_PC [7:0] $end
$var wire      1 -    valid  $end
$var wire      1 .    ready  $end
$var wire      1 /    isp_address  $end
$var wire      1 0    isp_data  $end
$var wire      1 1    isp_write  $end

$scope module IF $end
$var wire      1 2    report  $end
$var wire      1 3    ready  $end
$var wire      1 4    valid  $end
$var wire     28 5    inst_PC [27:0] $end
$var wire     32 6    instruction [31:0] $end
$var wire      1 7    isp_write  $end
$var wire     32 8    isp_data [31:0] $end
$var wire     28 9    isp_address [27:0] $end
$var wire     28 :    branch_target [27:0] $end
$var wire      1 ;    branch  $end
$var wire     28 <    JALR_target [27:0] $end
$var wire     28 =    JAL_target [27:0] $end
$var wire     28 >    program_address [27:0] $end
$var wire      2 ?    PC_select [1:0] $end
$var wire      1 @    start  $end
$var wire      1 A    reset  $end
$var wire      1 B    clock  $end
$var reg      28 C    old_PC [27:0] $end
$var reg       1 D    fetch  $end
$var reg      28 E    PC_reg [27:0] $end
$var wire     28 F    PC [27:0] $end
$var wire     28 G    PC_plus4 [27:0] $end
$var wire     28 H    inst_addr [27:0] $end
$var wire     28 I    out_addr [27:0] $end
$var reg      32 J    cycles [31:0] $end

$scope module i_mem_interface $end
$var wire      1 K    report  $end
$var wire     32 L    out_data [31:0] $end
$var wire     28 M    out_addr [27:0] $end
$var wire      1 N    ready  $end
$var wire      1 O    valid  $end
$var wire     32 P    in_data [31:0] $end
$var wire     28 Q    read_address [27:0] $end
$var wire     28 R    write_address [27:0] $end
$var wire      1 S    write  $end
$var wire      1 T    read  $end
$var wire      1 U    reset  $end
$var wire      1 V    clock  $end
$var reg      32 W    cycles [31:0] $end

$scope module RAM $end
$var wire      1 X    report  $end
$var wire     32 Y    writeData [31:0] $end
$var wire     28 Z    writeAddress [27:0] $end
$var wire      1 [    writeEnable  $end
$var wire     28 \    readAddress [27:0] $end
$var wire      1 ]    readEnable  $end
$var wire      1 ^    reset  $end
$var wire      1 _    clock  $end
$var wire     32 `    readData [31:0] $end
$var reg      32 a    cycles [31:0] $end

$scope begin RAM_WRITE $end
$upscope $end

$upscope $end

$upscope $end

$upscope $end

$upscope $end

$enddefinitions      $end
#0
$dumpvars
bx a
bx `
0_
1^
x]
b0 \
z[
b0z Z
b0z Y
1X
bx W
0V
1U
xT
zS
b0z R
b0 Q
b0z P
xO
xN
b0 M
bx L
1K
bx J
b0 I
b0 H
b100 G
b0 F
bx E
xD
bx C
0B
1A
1@
b0 ?
b0 >
b0 =
b0 <
0;
b10 :
b0z 9
b0z 8
z7
bx 6
b0 5
x4
x3
12
z1
z0
z/
x.
x-
b0 ,
bx +
1*
b10 )
0(
b0 '
b0 &
b0 %
b0 $
1#
1"
0!
$end
#1
1!
1_
1V
1B
b0 a
b0 W
0D
b0 E
b0 C
b0 J
0]
0T
b0 `
b0 L
b0 6
b0 +
#2
0!
0_
0V
0B
#3
1!
1_
1V
1B
#4
0!
0_
0V
0B
#5
1!
1_
1V
1B
#6
0!
0_
0V
0B
#7
1!
1_
1V
1B
#8
0"
0!
0^
0U
0A
0_
0V
0B
#9
1!
1_
1V
1B
b1 a
b1 W
1D
b1 J
1]
1T
0N
03
0.
1O
14
1-
bx `
bx L
bx 6
bx +
#10
0!
0_
0V
0B
#11
1!
1_
1V
1B
b10 a
b10 W
b10 J
#12
0!
0_
0V
0B
#13
1!
1_
1V
1B
b11 a
b11 W
b11 J
#14
0!
0_
0V
0B
#15
1!
1_
1V
1B
b100 a
b100 W
b100 J
#16
0!
0_
0V
0B
#17
1!
1_
1V
1B
b101 a
b101 W
b101 J
#18
0#
0!
0@
0_
0V
0B
#19
1!
1_
1V
1B
b1 $
b110 a
b110 W
b1 \
b1 Q
b1 H
b1000 G
b100 F
b100 E
b110 J
b1 ?
b1 M
b1 I
b100 5
b100 ,
#20
0!
0_
0V
0B
#21
1!
1_
1V
1B
b10 $
b111 a
b111 W
b10 \
b10 Q
b10 H
b1100 G
b1000 F
b1000 E
b100 C
b111 J
b10 ?
b10 M
b10 I
b1000 5
b1000 ,
#22
0!
0_
0V
0B
#23
1!
1_
1V
1B
b11 $
b1000 a
b1000 W
b0 \
b0 Q
b0 H
b100 G
b0 F
b0 E
b1000 C
b1000 J
b11 ?
b0 M
b0 I
b0 5
b0 ,
#24
0!
0_
0V
0B
#25
1!
1_
1V
1B
b0 $
b1001 a
b1001 W
b0 C
b1001 J
b0 ?
#26
0!
0_
0V
0B
#27
1!
1_
1V
1B
b1 $
b1010 a
b1010 W
b1 \
b1 Q
b1 H
b1000 G
b100 F
b100 E
b1010 J
b1 ?
b1 M
b1 I
b100 5
b100 ,
#28
0!
0_
0V
0B
#29
1!
1_
1V
1B
b1011 a
b1011 W
b10 \
b10 Q
b10 H
b1100 G
b1000 F
b1000 E
b100 C
b1011 J
b10 M
b10 I
b1000 5
b1000 ,
#30
0!
0_
0V
0B
#31
1!
1_
1V
1B
b1100 a
b1100 W
b11 \
b11 Q
b11 H
b10000 G
b1100 F
b1100 E
b1000 C
b1100 J
b11 M
b11 I
b1100 5
b1100 ,
#32
0!
0_
0V
0B
#33
1!
1_
1V
1B
b1101 a
b1101 W
b100 \
b100 Q
b100 H
b10100 G
b10000 F
b10000 E
b1100 C
b1101 J
b100 M
b100 I
b10000 5
b10000 ,
#34
0!
0_
0V
0B
#35
1!
1_
1V
1B
b1110 a
b1110 W
b101 \
b101 Q
b101 H
b11000 G
b10100 F
b10100 E
b10000 C
b1110 J
b101 M
b101 I
b10100 5
b10100 ,
#36
0!
0_
0V
0B
#37
1!
1_
1V
1B
b1111 a
b1111 W
b110 \
b110 Q
b110 H
b11100 G
b11000 F
b11000 E
b10100 C
b1111 J
b110 M
b110 I
b11000 5
b11000 ,
#38
0!
0_
0V
0B
#39
1!
1_
1V
1B
b10000 a
b10000 W
b111 \
b111 Q
b111 H
b100000 G
b11100 F
b11100 E
b11000 C
b10000 J
b111 M
b111 I
b11100 5
b11100 ,
#40
0!
0_
0V
0B
#41
1!
1_
1V
1B
b10001 a
b10001 W
b1000 \
b1000 Q
b1000 H
b100100 G
b100000 F
b100000 E
b11100 C
b10001 J
b1000 M
b1000 I
b100000 5
b100000 ,
#42
0!
0_
0V
0B
#43
1!
1_
1V
1B
b10010 a
b10010 W
b1001 \
b1001 Q
b1001 H
b101000 G
b100100 F
b100100 E
b100000 C
b10010 J
b1001 M
b1001 I
b100100 5
b100100 ,
#44
0!
0_
0V
0B
#45
1!
1_
1V
1B
b10011 a
b10011 W
b1010 \
b1010 Q
b1010 H
b101100 G
b101000 F
b101000 E
b100100 C
b10011 J
b1010 M
b1010 I
b101000 5
b101000 ,
#46
0!
0_
0V
0B
#47
1!
1_
1V
1B
b10100 a
b10100 W
b1011 \
b1011 Q
b1011 H
b110000 G
b101100 F
b101100 E
b101000 C
b10100 J
b1011 M
b1011 I
b101100 5
b101100 ,
#48
0!
0_
0V
0B
#49
1!
1_
1V
1B
b10101 a
b10101 W
b1100 \
b1100 Q
b1100 H
b110100 G
b110000 F
b110000 E
b101100 C
b10101 J
b1100 M
b1100 I
b110000 5
b110000 ,
#50
0!
0_
0V
0B
#51
1!
1_
1V
1B
b10110 a
b10110 W
b1101 \
b1101 Q
b1101 H
b111000 G
b110100 F
b110100 E
b110000 C
b10110 J
b1101 M
b1101 I
b110100 5
b110100 ,
#52
0!
0_
0V
0B
#53
1!
1_
1V
1B
b10111 a
b10111 W
b1110 \
b1110 Q
b1110 H
b111100 G
b111000 F
b111000 E
b110100 C
b10111 J
b1110 M
b1110 I
b111000 5
b111000 ,
#54
0!
0_
0V
0B
#55
1!
1_
1V
1B
b11000 a
b11000 W
b1111 \
b1111 Q
b1111 H
b1000000 G
b111100 F
b111100 E
b111000 C
b11000 J
b1111 M
b1111 I
b111100 5
b111100 ,
#56
0!
0_
0V
0B
#57
1!
1_
1V
1B
b11001 a
b11001 W
b10000 \
b10000 Q
b10000 H
b1000100 G
b1000000 F
b1000000 E
b111100 C
b11001 J
b10000 M
b10000 I
b1000000 5
b1000000 ,
#58
0!
0_
0V
0B
#59
1!
1_
1V
1B
b11010 a
b11010 W
b10001 \
b10001 Q
b10001 H
b1001000 G
b1000100 F
b1000100 E
b1000000 C
b11010 J
b10001 M
b10001 I
b1000100 5
b1000100 ,
#60
0!
0_
0V
0B
#61
1!
1_
1V
1B
b11011 a
b11011 W
b10010 \
b10010 Q
b10010 H
b1001100 G
b1001000 F
b1001000 E
b1000100 C
b11011 J
b10010 M
b10010 I
b1001000 5
b1001000 ,
#62
0!
0_
0V
0B
#63
1!
1_
1V
1B
b11100 a
b11100 W
b10011 \
b10011 Q
b10011 H
b1010000 G
b1001100 F
b1001100 E
b1001000 C
b11100 J
b10011 M
b10011 I
b1001100 5
b1001100 ,
#64
0!
0_
0V
0B
#65
1!
1_
1V
1B
b11101 a
b11101 W
b10100 \
b10100 Q
b10100 H
b1010100 G
b1010000 F
b1010000 E
b1001100 C
b11101 J
b10100 M
b10100 I
b1010000 5
b1010000 ,
#66
0!
0_
0V
0B
#67
1!
1_
1V
1B
b11110 a
b11110 W
b10101 \
b10101 Q
b10101 H
b1011000 G
b1010100 F
b1010100 E
b1010000 C
b11110 J
b10101 M
b10101 I
b1010100 5
b1010100 ,
#68
0!
0_
0V
0B
#69
1!
1_
1V
1B
b11111 a
b11111 W
b10110 \
b10110 Q
b10110 H
b1011100 G
b1011000 F
b1011000 E
b1010100 C
b11111 J
b10110 M
b10110 I
b1011000 5
b1011000 ,
#70
0!
0_
0V
0B
#71
1!
1_
1V
1B
b100000 a
b100000 W
b10111 \
b10111 Q
b10111 H
b1100000 G
b1011100 F
b1011100 E
b1011000 C
b100000 J
b10111 M
b10111 I
b1011100 5
b1011100 ,
#72
0!
0_
0V
0B
#73
1!
1_
1V
1B
b100001 a
b100001 W
b11000 \
b11000 Q
b11000 H
b1100100 G
b1100000 F
b1100000 E
b1011100 C
b100001 J
b11000 M
b11000 I
b1100000 5
b1100000 ,
#74
0!
0_
0V
0B
#75
1!
1_
1V
1B
b100010 a
b100010 W
b11001 \
b11001 Q
b11001 H
b1101000 G
b1100100 F
b1100100 E
b1100000 C
b100010 J
b11001 M
b11001 I
b1100100 5
b1100100 ,
#76
0!
0_
0V
0B
#77
1!
1_
1V
1B
b100011 a
b100011 W
b11010 \
b11010 Q
b11010 H
b1101100 G
b1101000 F
b1101000 E
b1100100 C
b100011 J
b11010 M
b11010 I
b1101000 5
b1101000 ,
#78
0!
0_
0V
0B
#79
1!
1_
1V
1B
b100100 a
b100100 W
b11011 \
b11011 Q
b11011 H
b1110000 G
b1101100 F
b1101100 E
b1101000 C
b100100 J
b11011 M
b11011 I
b1101100 5
b1101100 ,
#80
0!
0_
0V
0B
#81
1!
1_
1V
1B
b100101 a
b100101 W
b11100 \
b11100 Q
b11100 H
b1110100 G
b1110000 F
b1110000 E
b1101100 C
b100101 J
b11100 M
b11100 I
b1110000 5
b1110000 ,
#82
0!
0_
0V
0B
#83
1!
1_
1V
1B
b100110 a
b100110 W
b11101 \
b11101 Q
b11101 H
b1111000 G
b1110100 F
b1110100 E
b1110000 C
b100110 J
b11101 M
b11101 I
b1110100 5
b1110100 ,
#84
0!
0_
0V
0B
#85
1!
1_
1V
1B
b100111 a
b100111 W
b11110 \
b11110 Q
b11110 H
b1111100 G
b1111000 F
b1111000 E
b1110100 C
b100111 J
b11110 M
b11110 I
b1111000 5
b1111000 ,
#86
0!
0_
0V
0B
#87
1!
1_
1V
1B
b101000 a
b101000 W
b11111 \
b11111 Q
b11111 H
b10000000 G
b1111100 F
b1111100 E
b1111000 C
b101000 J
b11111 M
b11111 I
b1111100 5
b1111100 ,
#88
0!
0_
0V
0B
#89
1!
1_
1V
1B
b101001 a
b101001 W
b100000 \
b100000 Q
b100000 H
b10000100 G
b10000000 F
b10000000 E
b1111100 C
b101001 J
b100000 M
b100000 I
b10000000 5
b10000000 ,
#90
0!
0_
0V
0B
#91
1!
1_
1V
1B
b101010 a
b101010 W
b100001 \
b100001 Q
b100001 H
b10001000 G
b10000100 F
b10000100 E
b10000000 C
b101010 J
b100001 M
b100001 I
b10000100 5
b10000100 ,
#92
0!
0_
0V
0B
#93
1!
1_
1V
1B
b101011 a
b101011 W
b100010 \
b100010 Q
b100010 H
b10001100 G
b10001000 F
b10001000 E
b10000100 C
b101011 J
b100010 M
b100010 I
b10001000 5
b10001000 ,
#94
0!
0_
0V
0B
#95
1!
1_
1V
1B
b101100 a
b101100 W
b100011 \
b100011 Q
b100011 H
b10010000 G
b10001100 F
b10001100 E
b10001000 C
b101100 J
b100011 M
b100011 I
b10001100 5
b10001100 ,
#96
0!
0_
0V
0B
#97
1!
1_
1V
1B
b101101 a
b101101 W
b100100 \
b100100 Q
b100100 H
b10010100 G
b10010000 F
b10010000 E
b10001100 C
b101101 J
b100100 M
b100100 I
b10010000 5
b10010000 ,
#98
0!
0_
0V
0B
#99
1!
1_
1V
1B
b101110 a
b101110 W
b100101 \
b100101 Q
b100101 H
b10011000 G
b10010100 F
b10010100 E
b10010000 C
b101110 J
b100101 M
b100101 I
b10010100 5
b10010100 ,
#100
0!
0_
0V
0B
#101
1!
1_
1V
1B
b101111 a
b101111 W
b100110 \
b100110 Q
b100110 H
b10011100 G
b10011000 F
b10011000 E
b10010100 C
b101111 J
b100110 M
b100110 I
b10011000 5
b10011000 ,
#102
0!
0_
0V
0B
#103
1!
1_
1V
1B
b110000 a
b110000 W
b100111 \
b100111 Q
b100111 H
b10100000 G
b10011100 F
b10011100 E
b10011000 C
b110000 J
b100111 M
b100111 I
b10011100 5
b10011100 ,
#104
0!
0_
0V
0B
#105
1!
1_
1V
1B
b110001 a
b110001 W
b101000 \
b101000 Q
b101000 H
b10100100 G
b10100000 F
b10100000 E
b10011100 C
b110001 J
b101000 M
b101000 I
b10100000 5
b10100000 ,
#106
0!
0_
0V
0B
#107
1!
1_
1V
1B
b110010 a
b110010 W
b101001 \
b101001 Q
b101001 H
b10101000 G
b10100100 F
b10100100 E
b10100000 C
b110010 J
b101001 M
b101001 I
b10100100 5
b10100100 ,
#108
0!
0_
0V
0B
#109
1!
1_
1V
1B
b110011 a
b110011 W
b101010 \
b101010 Q
b101010 H
b10101100 G
b10101000 F
b10101000 E
b10100100 C
b110011 J
b101010 M
b101010 I
b10101000 5
b10101000 ,
#110
0!
0_
0V
0B
#111
1!
1_
1V
1B
b110100 a
b110100 W
b101011 \
b101011 Q
b101011 H
b10110000 G
b10101100 F
b10101100 E
b10101000 C
b110100 J
b101011 M
b101011 I
b10101100 5
b10101100 ,
#112
0!
0_
0V
0B
#113
1!
1_
1V
1B
b110101 a
b110101 W
b101100 \
b101100 Q
b101100 H
b10110100 G
b10110000 F
b10110000 E
b10101100 C
b110101 J
b101100 M
b101100 I
b10110000 5
b10110000 ,
#114
0!
0_
0V
0B
#115
1!
1_
1V
1B
b110110 a
b110110 W
b101101 \
b101101 Q
b101101 H
b10111000 G
b10110100 F
b10110100 E
b10110000 C
b110110 J
b101101 M
b101101 I
b10110100 5
b10110100 ,
#116
0!
0_
0V
0B
#117
1!
1_
1V
1B
b110111 a
b110111 W
b101110 \
b101110 Q
b101110 H
b10111100 G
b10111000 F
b10111000 E
b10110100 C
b110111 J
b101110 M
b101110 I
b10111000 5
b10111000 ,
#118
0!
0_
0V
0B
#119
1!
1_
1V
1B
b111000 a
b111000 W
b101111 \
b101111 Q
b101111 H
b11000000 G
b10111100 F
b10111100 E
b10111000 C
b111000 J
b101111 M
b101111 I
b10111100 5
b10111100 ,
#120
0!
0_
0V
0B
#121
1!
1_
1V
1B
b111001 a
b111001 W
b110000 \
b110000 Q
b110000 H
b11000100 G
b11000000 F
b11000000 E
b10111100 C
b111001 J
b110000 M
b110000 I
b11000000 5
b11000000 ,
#122
0!
0_
0V
0B
#123
1!
1_
1V
1B
b111010 a
b111010 W
b110001 \
b110001 Q
b110001 H
b11001000 G
b11000100 F
b11000100 E
b11000000 C
b111010 J
b110001 M
b110001 I
b11000100 5
b11000100 ,
#124
0!
0_
0V
0B
#125
1!
1_
1V
1B
b111011 a
b111011 W
b110010 \
b110010 Q
b110010 H
b11001100 G
b11001000 F
b11001000 E
b11000100 C
b111011 J
b110010 M
b110010 I
b11001000 5
b11001000 ,
#126
0!
0_
0V
0B
#127
1!
1_
1V
1B
b111100 a
b111100 W
b110011 \
b110011 Q
b110011 H
b11010000 G
b11001100 F
b11001100 E
b11001000 C
b111100 J
b110011 M
b110011 I
b11001100 5
b11001100 ,
#128
0!
0_
0V
0B
#129
1!
1_
1V
1B
b111101 a
b111101 W
b110100 \
b110100 Q
b110100 H
b11010100 G
b11010000 F
b11010000 E
b11001100 C
b111101 J
b110100 M
b110100 I
b11010000 5
b11010000 ,
#130
0!
0_
0V
0B
#131
1!
1_
1V
1B
b111110 a
b111110 W
b110101 \
b110101 Q
b110101 H
b11011000 G
b11010100 F
b11010100 E
b11010000 C
b111110 J
b110101 M
b110101 I
b11010100 5
b11010100 ,
#132
0!
0_
0V
0B
#133
1!
1_
1V
1B
b111111 a
b111111 W
b110110 \
b110110 Q
b110110 H
b11011100 G
b11011000 F
b11011000 E
b11010100 C
b111111 J
b110110 M
b110110 I
b11011000 5
b11011000 ,
#134
0!
0_
0V
0B
#135
1!
1_
1V
1B
b1000000 a
b1000000 W
b110111 \
b110111 Q
b110111 H
b11100000 G
b11011100 F
b11011100 E
b11011000 C
b1000000 J
b110111 M
b110111 I
b11011100 5
b11011100 ,
#136
0!
0_
0V
0B
#137
1!
1_
1V
1B
b1000001 a
b1000001 W
b111000 \
b111000 Q
b111000 H
b11100100 G
b11100000 F
b11100000 E
b11011100 C
b1000001 J
b111000 M
b111000 I
b11100000 5
b11100000 ,
#138
0!
0_
0V
0B
#139
1!
1_
1V
1B
b1000010 a
b1000010 W
b111001 \
b111001 Q
b111001 H
b11101000 G
b11100100 F
b11100100 E
b11100000 C
b1000010 J
b111001 M
b111001 I
b11100100 5
b11100100 ,
#140
0!
0_
0V
0B
#141
1!
1_
1V
1B
b1000011 a
b1000011 W
b111010 \
b111010 Q
b111010 H
b11101100 G
b11101000 F
b11101000 E
b11100100 C
b1000011 J
b111010 M
b111010 I
b11101000 5
b11101000 ,
#142
0!
0_
0V
0B
#143
1!
1_
1V
1B
b1000100 a
b1000100 W
b111011 \
b111011 Q
b111011 H
b11110000 G
b11101100 F
b11101100 E
b11101000 C
b1000100 J
b111011 M
b111011 I
b11101100 5
b11101100 ,
#144
0!
0_
0V
0B
#145
1!
1_
1V
1B
b1000101 a
b1000101 W
b111100 \
b111100 Q
b111100 H
b11110100 G
b11110000 F
b11110000 E
b11101100 C
b1000101 J
b111100 M
b111100 I
b11110000 5
b11110000 ,
#146
0!
0_
0V
0B
