BRISC-V_single_cycle_base/src/writeback.v
/** @module : writeback
 *  @author : Adaptive & Secure Computing Systems (ASCS) Laboratory
 
 *  Copyright (c) 2018 BRISC-V (ASCS/ECE/BU)
 *  Permission is hereby granted, free of charge, to any person obtaining a copy
 *  of this software and associated documentation files (the "Software"), to deal
 *  in the Software without restriction, including without limitation the rights
 *  to use, copy, modify, merge, publish, distribute, sublicense, and/or sell
 *  copies of the Software, and to permit persons to whom the Software is
 *  furnished to do so, subject to the following conditions:
 *  The above copyright notice and this permission notice shall be included in
 *  all copies or substantial portions of the Software.

 *  THE SOFTWARE IS PROVIDED "AS IS", WITHOUT WARRANTY OF ANY KIND, EXPRESS OR
 *  IMPLIED, INCLUDING BUT NOT LIMITED TO THE WARRANTIES OF MERCHANTABILITY,
 *  FITNESS FOR A PARTICULAR PURPOSE AND NONINFRINGEMENT. IN NO EVENT SHALL THE
 *  AUTHORS OR COPYRIGHT HOLDERS BE LIABLE FOR ANY CLAIM, DAMAGES OR OTHER
 *  LIABILITY, WHETHER IN AN ACTION OF CONTRACT, TORT OR OTHERWISE, ARISING FROM,
 *  OUT OF OR IN CONNECTION WITH THE SOFTWARE OR THE USE OR OTHER DEALINGS IN
 *  THE SOFTWARE.
 */
 module writeback_unit (
      clock, reset,  
      opWrite,
      opSel, 
      opReg, 
      ALU_Result, 
      memory_data, 
      write, write_reg, write_data, 
      report
); 
 
parameter  CORE = 0, DATA_WIDTH = 32;
input  clock; 
input  reset; 

input  opWrite; 
input  opSel; 
input  [4:0]  opReg;
input  [DATA_WIDTH-1:0] ALU_Result;
input  [DATA_WIDTH-1:0] memory_data; 

output  write;
output  [4:0]  write_reg;
output  [DATA_WIDTH-1:0] write_data;

input report; 

assign write_data = opSel? memory_data : ALU_Result; 
assign write_reg  = opReg; 
assign write      = opWrite; 

reg [31: 0] cycles; 
always @ (posedge clock) begin 
    cycles <= reset? 0 : cycles + 1; 
    if (report)begin
        $display ("------ Core %d Writeback Unit - Current Cycle %d ----", CORE, cycles); 
        $display ("| opSel       [%b]", opSel);
        $display ("| opReg       [%b]", opReg);
        $display ("| ALU_Result  [%d]", ALU_Result);
        $display ("| Memory_data [%d]", memory_data);
        $display ("| write       [%b]", write);
        $display ("| write_reg   [%d]", write_reg);
        $display ("| write_data  [%d]", write_data);
        $display ("----------------------------------------------------------------------");
    end
end

endmodule

 //------------------------------------------------mem_write test bench-------------------------------------//
module tb_writeback_unit (); 

reg clk, reset;  
reg  opWrite; 
reg  opSel; 
reg  [4:0]  opReg;
reg  [31:0] ALU_Result;
reg  [31:0] memory_data; 

wire  write;
wire  [4:0]  write_reg;
wire  [31:0] write_data;

reg  report; 

writeback_unit #(0, 32) WB (
     .clock(clk),
     .reset(reset), 
     .opWrite(opWrite),
      .opSel(opSel), 
      .opReg(opReg), 
      .ALU_Result(ALU_Result), 
      .memory_data(memory_data), 
      .write(write),
       .write_reg(write_reg),
       .write_data(write_data), 
      .report(report)
);

// Clock generator
always #1 clk = ~clk;

initial begin
  $dumpfile ("writeback.vcd");
  $dumpvars();
  clk   = 0;
  reset = 1;
  opWrite       = 0; 
  opSel         = 0; 
  opReg         = 0; 
  ALU_Result    = 0; 
  memory_data   = 0; 
  report        = 1; 
  
  #10 reset = 0; 
  $display (" --- Start --- ");
  repeat (1) @ (posedge clk);
  
  opWrite       = 1; 
  opSel         = 0; 
  opReg         = 3; 
  ALU_Result    = 5; 
  memory_data   = 9; 
  repeat (1) @ (posedge clk);
  
  opWrite       = 0; 
  opSel         = 1; 
  opReg         = 0; 
  ALU_Result    = 4; 
  memory_data   = 8;
  repeat (1) @ (posedge clk);
  #300 $finish;
  
  end

endmodule

BRISC-V_single_cycle_base/src/writeback.vcd
$date
      Thu Mar 23 17:15:49 2023

$end
$version
      Veriwell 2.8.7
$end
$timescale
      1s
$end


$scope module tb_writeback_unit $end
$var reg       1 !    clk  $end
$var reg       1 "    reset  $end
$var reg       1 #    opWrite  $end
$var reg       1 $    opSel  $end
$var reg       5 %    opReg [4:0] $end
$var reg      32 &    ALU_Result [31:0] $end
$var reg      32 '    memory_data [31:0] $end
$var wire      1 (    write  $end
$var wire      5 )    write_reg [4:0] $end
$var wire     32 *    write_data [31:0] $end
$var reg       1 +    report  $end

$scope module WB $end
$var wire      1 ,    report  $end
$var wire     32 -    write_data [31:0] $end
$var wire      5 .    write_reg [4:0] $end
$var wire      1 /    write  $end
$var wire     32 0    memory_data [31:0] $end
$var wire     32 1    ALU_Result [31:0] $end
$var wire      5 2    opReg [4:0] $end
$var wire      1 3    opSel  $end
$var wire      1 4    opWrite  $end
$var wire      1 5    reset  $end
$var wire      1 6    clock  $end
$var reg      32 7    cycles [31:0] $end
$upscope $end

$upscope $end

$enddefinitions      $end
#0
$dumpvars
bx 7
06
15
04
03
b0 2
b0 1
b0 0
0/
b0 .
b0 -
1,
1+
b0 *
b0 )
0(
b0 '
b0 &
b0 %
0$
0#
1"
0!
$end
#1
1!
16
b0 7
#2
0!
06
#3
1!
16
#4
0!
06
#5
1!
16
#6
0!
06
#7
1!
16
#8
0!
06
#9
1!
16
#10
0"
0!
05
06
#11
1!
1#
b11 %
b101 &
b1001 '
16
14
b11 2
b101 1
b1001 0
1/
1(
b11 .
b11 )
b101 -
b101 *
b1 7
#12
0!
06
#13
1!
0#
1$
b0 %
b100 &
b1000 '
16
04
13
b0 2
b100 1
b1000 0
0/
0(
b1000 -
b1000 *
b0 .
b0 )
b10 7
#14
0!
06
#15
1!
16
b11 7
#16
0!
06
#17
1!
16
b100 7
#18
0!
06
#19
1!
16
b101 7
#20
0!
06
#21
1!
16
b110 7
#22
0!
06
#23
1!
16
b111 7
#24
0!
06
#25
1!
16
b1000 7
#26
0!
06
#27
1!
16
b1001 7
#28
0!
06
#29
1!
16
b1010 7
#30
0!
06
#31
1!
16
b1011 7
#32
0!
06
#33
1!
16
b1100 7
#34
0!
06
#35
1!
16
b1101 7
#36
0!
06
#37
1!
16
b1110 7
#38
0!
06
#39
1!
16
b1111 7
#40
0!
06
#41
1!
16
b10000 7
#42
0!
06
#43
1!
16
b10001 7
#44
0!
06
#45
1!
16
b10010 7
#46
0!
06
#47
1!
16
b10011 7
#48
0!
06
#49
1!
16
b10100 7
#50
0!
06
#51
1!
16
b10101 7
#52
0!
06
#53
1!
16
b10110 7
#54
0!
06
#55
1!
16
b10111 7
#56
0!
06
#57
1!
16
b11000 7
#58
0!
06
#59
1!
16
b11001 7
#60
0!
06
#61
1!
16
b11010 7
#62
0!
06
#63
1!
16
b11011 7
#64
0!
06
#65
1!
16
b11100 7
#66
0!
06
#67
1!
16
b11101 7
#68
0!
06
#69
1!
16
b11110 7
#70
0!
06
#71
1!
16
b11111 7
#72
0!
06
#73
1!
16
b100000 7
#74
0!
06
#75
1!
16
b100001 7
#76
0!
06
#77
1!
16
b100010 7
#78
0!
06
#79
1!
16
b100011 7
#80
0!
06
#81
1!
16
b100100 7
#82
0!
06
#83
1!
16
b100101 7
#84
0!
06
#85
1!
16
b100110 7
#86
0!
06
#87
1!
16
b100111 7
#88
0!
06
#89
1!
16
b101000 7
#90
0!
06
#91
1!
16
b101001 7
#92
0!
06
#93
1!
16
b101010 7
#94
0!
06
#95
1!
16
b101011 7
#96
0!
06
#97
1!
16
b101100 7
#98
0!
06
#99
1!
16
b101101 7
#100
0!
06
#101
1!
16
b101110 7
#102
0!
06
#103
1!
16
b101111 7
#104
0!
06
#105
1!
16
b110000 7
#106
0!
06
#107
1!
16
b110001 7
#108
0!
06
#109
1!
16
b110010 7
#110
0!
06
#111
1!
16
b110011 7
#112
0!
06
#113
1!
16
b110100 7
#114
0!
06
#115
1!
16
b110101 7
#116
0!
06
#117
1!
16
b110110 7
#118
0!
06
#119
1!
16
b110111 7
#120
0!
06
#121
1!
16
b111000 7
#122
0!
06
#123
1!
16
b111001 7
#124
0!
06
#125
1!
16
b111010 7
#126
0!
06
#127
1!
16
b111011 7
#128
0!
06
#129
1!
16
b111100 7
#130
0!
06
#131
1!
16
b111101 7
#132
0!
06
#133
1!
16
b111110 7
#134
0!
06
#135
1!
16
b111111 7
#136
0!
06
#137
1!
16
b1000000 7
#138
0!
06
#139
1!
16
b1000001 7
#140
0!
06
#141
1!
16
b1000010 7
#142
0!
06
#143
1!
16
b1000011 7
#144
0!
06
#145
1!
16
b1000100 7
#146
0!
06
#147
1!
16
b1000101 7
#148
0!
06
#149
1!
16
b1000110 7
#150
0!
06
#151
1!
16
b1000111 7
#152
0!
06
#153
1!
16
b1001000 7
#154
0!
06
#155
1!
16
b1001001 7
#156
0!
06
#157
1!
16
b1001010 7
#158
0!
06
#159
1!
16
b1001011 7
#160
0!
06
#161
1!
16
b1001100 7
#162
0!
06
#163
1!
16
b1001101 7
#164
0!
06
#165
1!
16
b1001110 7
#166
0!
06
#167
1!
16
b1001111 7
#168
0!
06
#169
1!
16
b1010000 7
#170
0!
06
#171
1!
16
b1010001 7
#172
0!
06
#173
1!
16
b1010010 7
#174
0!
06
#175
1!
16
b1010011 7
#176
0!
06
#177
1!
16
b1010100 7
#178
0!
06
#179
1!
16
b1010101 7
#180
0!
06
#181
1!
16
b1010110 7
#182
0!
06
#183
1!
16
b1010111 7
#184
0!
06
#185
1!
16
b1011000 7
#186
0!
06
#187
1!
16
b1011001 7
#188
0!
06
#189
1!
16
b1011010 7
#190
0!
06
#191
1!
16
b1011011 7
#192
0!
06
#193
1!
16
b1011100 7
#194
0!
06
#195
1!
16
b1011101 7
#196
0!
06
#197
1!
16
b1011110 7
#198
0!
06
#199
1!
16
b1011111 7
#200
0!
06
#201
1!
16
b1100000 7
#202
0!
06
#203
1!
16
b1100001 7
#204
0!
06
#205
1!
16
b1100010 7
#206
0!
06
#207
1!
16
b1100011 7
#208
0!
06
#209
1!
16
b1100100 7
#210
0!
06
#211
1!
16
b1100101 7
#212
0!
06
#213
1!
16
b1100110 7
#214
0!
06
#215
1!
16
b1100111 7
#216
0!
06
#217
1!
16
b1101000 7
#218
0!
06
#219
1!
16
b1101001 7
#220
0!
06
#221
1!
16
b1101010 7
#222
0!
06
#223
1!
16
b1101011 7
#224
0!
06
#225
1!
16
b1101100 7
#226
0!
06
#227
1!
16
b1101101 7
#228
0!
06
#229
1!
16
b1101110 7
#230
0!
06
#231
1!
16
b1101111 7
#232
0!
06
#233
1!
16
b1110000 7
#234
0!
06
#235
1!
16
b1110001 7
#236
0!
06
#237
1!
16
b1110010 7
#238
0!
06
#239
1!
16
b1110011 7
#240
0!
06
#241
1!
16
b1110100 7
#242
0!
06
#243
1!
16
b1110101 7
#244
0!
06
#245
1!
16
b1110110 7
#246
0!
06
#247
1!
16
b1110111 7
#248
0!
06
#249
1!
16
b1111000 7
#250
0!
06
#251
1!
16
b1111001 7
#252
0!
06
#253
1!
16
b1111010 7
#254
0!
06
#255
1!
16
b1111011 7
#256
0!
06
#257
1!
16
b1111100 7
#258
0!
06
#259
1!
16
b1111101 7
#260
0!
06
#261
1!
16
b1111110 7
#262
0!
06
#263
1!
16
b1111111 7
#264
0!
06
#265
1!
16
b10000000 7
#266
0!
06
#267
1!
16
b10000001 7
#268
0!
06
#269
1!
16
b10000010 7
#270
0!
06
#271
1!
16
b10000011 7
#272
0!
06
#273
1!
16
b10000100 7
#274
0!
06
#275
1!
16
b10000101 7
#276
0!
06
#277
1!
16
b10000110 7
#278
0!
06
#279
1!
16
b10000111 7
#280
0!
06
#281
1!
16
b10001000 7
#282
0!
06
#283
1!
16
b10001001 7
#284
0!
06
#285
1!
16
b10001010 7
#286
0!
06
#287
1!
16
b10001011 7
#288
0!
06
#289
1!
16
b10001100 7
#290
0!
06
#291
1!
16
b10001101 7
#292
0!
06
#293
1!
16
b10001110 7
#294
0!
06
#295
1!
16
b10001111 7
#296
0!
06
#297
1!
16
b10010000 7
#298
0!
06
#299
1!
16
b10010001 7
#300
0!
06
#301
1!
16
b10010010 7
#302
0!
06
#303
1!
16
b10010011 7
#304
0!
06
#305
1!
16
b10010100 7
#306
0!
06
#307
1!
16
b10010101 7
#308
0!
06
#309
1!
16
b10010110 7
#310
0!
06
#311
1!
16
b10010111 7
#312
0!
06
#313
1!
16
b10011000 7
